<?xml version='1.0' encoding='utf-8'?>
<hierarchy rotation="0">
  <node index="0" text="" resource-id="" class="android.widget.FrameLayout" package="com.google.android.apps.magazines" content-desc="" checkable="false" checked="false" clickable="false" enabled="true" focusable="false" focused="false" scrollable="false" long-clickable="false" password="false" selected="false" bounds="[0,0][1080,1794]">
    <node index="0" text="" resource-id="" class="android.widget.LinearLayout" package="com.google.android.apps.magazines" content-desc="" checkable="false" checked="false" clickable="false" enabled="true" focusable="false" focused="false" scrollable="false" long-clickable="false" password="false" selected="false" bounds="[0,0][1080,1794]">
      <node index="0" text="" resource-id="" class="android.widget.FrameLayout" package="com.google.android.apps.magazines" content-desc="" checkable="false" checked="false" clickable="false" enabled="true" focusable="false" focused="false" scrollable="false" long-clickable="false" password="false" selected="false" bounds="[0,0][1080,1794]">
        <node index="0" text="" resource-id="com.google.android.apps.magazines:id/action_bar_root" class="android.widget.LinearLayout" package="com.google.android.apps.magazines" content-desc="" checkable="false" checked="false" clickable="false" enabled="true" focusable="false" focused="false" scrollable="false" long-clickable="false" password="false" selected="false" bounds="[0,0][1080,1794]">
          <node index="0" text="" resource-id="android:id/content" class="android.widget.FrameLayout" package="com.google.android.apps.magazines" content-desc="" checkable="false" checked="false" clickable="false" enabled="true" focusable="false" focused="false" scrollable="false" long-clickable="false" password="false" selected="false" bounds="[0,0][1080,1794]">
            <node index="0" text="" resource-id="com.google.android.apps.magazines:id/edition_fragment" class="android.widget.ScrollView" package="com.google.android.apps.magazines" content-desc="" checkable="false" checked="false" clickable="false" enabled="true" focusable="false" focused="false" scrollable="true" long-clickable="false" password="false" selected="false" bounds="[0,0][1080,1794]">
              <node index="0" text="" resource-id="com.google.android.apps.magazines:id/appbar" class="android.widget.LinearLayout" package="com.google.android.apps.magazines" content-desc="" checkable="false" checked="false" clickable="false" enabled="true" focusable="true" focused="false" scrollable="false" long-clickable="false" password="false" selected="false" bounds="[0,0][1080,437]">
                <node index="0" text="" resource-id="com.google.android.apps.magazines:id/collapsing_toolbar" class="android.widget.FrameLayout" package="com.google.android.apps.magazines" content-desc="" checkable="false" checked="false" clickable="false" enabled="true" focusable="false" focused="false" scrollable="false" long-clickable="false" password="false" selected="false" bounds="[0,0][1080,437]">
                  <node index="0" text="" resource-id="com.google.android.apps.magazines:id/edition_pager_header" class="android.widget.FrameLayout" package="com.google.android.apps.magazines" content-desc="" checkable="false" checked="false" clickable="false" enabled="true" focusable="false" focused="false" scrollable="false" long-clickable="false" password="false" selected="false" bounds="[0,0][1080,437]">
                    <node index="0" text="" resource-id="com.google.android.apps.magazines:id/edition_pager_header_default_content" class="android.widget.LinearLayout" package="com.google.android.apps.magazines" content-desc="" checkable="false" checked="false" clickable="false" enabled="true" focusable="false" focused="false" scrollable="false" long-clickable="false" password="false" selected="false" bounds="[63,126][1017,279]">
                      <node index="0" text="" resource-id="com.google.android.apps.magazines:id/edition_pager_header_icon_label_frame" class="android.widget.LinearLayout" package="com.google.android.apps.magazines" content-desc="" checkable="false" checked="false" clickable="false" enabled="true" focusable="false" focused="false" scrollable="false" long-clickable="false" password="false" selected="false" bounds="[63,189][1017,279]">
                        <node index="0" text="" resource-id="com.google.android.apps.magazines:id/edition_pager_header_icon" class="android.widget.FrameLayout" package="com.google.android.apps.magazines" content-desc="The New York Times" checkable="false" checked="false" clickable="false" enabled="true" focusable="false" focused="false" scrollable="false" long-clickable="false" password="false" selected="false" bounds="[212,189][868,279]">
                          <node index="0" text="" resource-id="com.google.android.apps.magazines:id/edition_icon" class="android.widget.FrameLayout" package="com.google.android.apps.magazines" content-desc="" checkable="false" checked="false" clickable="false" enabled="true" focusable="false" focused="false" scrollable="false" long-clickable="false" password="false" selected="false" bounds="[212,189][868,279]">
                            <node index="0" text="" resource-id="" class="android.widget.FrameLayout" package="com.google.android.apps.magazines" content-desc="" checkable="false" checked="false" clickable="false" enabled="true" focusable="false" focused="false" scrollable="false" long-clickable="false" password="false" selected="false" bounds="[212,189][868,279]">
                              <node index="0" text="" resource-id="com.google.android.apps.magazines:id/rect_icon" class="android.widget.ImageView" package="com.google.android.apps.magazines" content-desc="" checkable="false" checked="false" clickable="false" enabled="true" focusable="false" focused="false" scrollable="false" long-clickable="false" password="false" selected="false" bounds="[212,189][868,279]"/>
                            </node>
                          </node>
                        </node>
                      </node>
                    </node>
                  </node>
                  <node index="1" text="" resource-id="com.google.android.apps.magazines:id/toolbar" class="android.view.ViewGroup" package="com.google.android.apps.magazines" content-desc="" checkable="false" checked="false" clickable="false" enabled="true" focusable="false" focused="false" scrollable="false" long-clickable="false" password="false" selected="false" bounds="[0,63][1080,231]">
                    <node index="0" text="" resource-id="" class="android.widget.ImageButton" package="com.google.android.apps.magazines" content-desc="Navigate up" checkable="false" checked="false" clickable="true" enabled="true" focusable="true" focused="false" scrollable="false" long-clickable="false" password="false" selected="false" bounds="[0,73][147,220]"/>
                    <node index="2" text="" resource-id="" class="android.support.v7.widget.LinearLayoutCompat" package="com.google.android.apps.magazines" content-desc="" checkable="false" checked="false" clickable="false" enabled="true" focusable="false" focused="false" scrollable="false" long-clickable="false" password="false" selected="false" bounds="[848,73][1080,220]">
                      <node index="0" text="" resource-id="com.google.android.apps.magazines:id/menu_add_edition" class="android.widget.Button" package="com.google.android.apps.magazines" content-desc="Follow" checkable="false" checked="false" clickable="true" enabled="true" focusable="true" focused="false" scrollable="false" long-clickable="false" password="false" selected="false" bounds="[848,83][975,209]"/>
                      <node index="1" text="" resource-id="" class="android.widget.ImageView" package="com.google.android.apps.magazines" content-desc="More options" checkable="false" checked="false" clickable="true" enabled="true" focusable="true" focused="false" scrollable="false" long-clickable="true" password="false" selected="false" bounds="[975,83][1080,209]"/>
                    </node>
                  </node>
                  <node index="2" text="" resource-id="com.google.android.apps.magazines:id/tab_layout" class="android.widget.HorizontalScrollView" package="com.google.android.apps.magazines" content-desc="" checkable="false" checked="false" clickable="false" enabled="true" focusable="true" focused="false" scrollable="true" long-clickable="false" password="false" selected="false" bounds="[0,311][1080,437]">
                    <node index="0" text="" resource-id="" class="android.widget.LinearLayout" package="com.google.android.apps.magazines" content-desc="" checkable="false" checked="false" clickable="false" enabled="true" focusable="false" focused="false" scrollable="false" long-clickable="false" password="false" selected="false" bounds="[0,311][1080,437]">
                      <node index="0" text="" resource-id="" class="android.widget.LinearLayout" package="com.google.android.apps.magazines" content-desc="Top News" checkable="false" checked="false" clickable="false" enabled="true" focusable="true" focused="false" scrollable="false" long-clickable="false" password="false" selected="true" bounds="[21,311][278,437]">
                        <node index="0" text="Top News" resource-id="" class="android.widget.TextView" package="com.google.android.apps.magazines" content-desc="" checkable="false" checked="false" clickable="false" enabled="true" focusable="false" focused="false" scrollable="false" long-clickable="false" password="false" selected="true" bounds="[63,351][236,397]"/>
                      </node>
                      <node index="1" text="" resource-id="" class="android.widget.LinearLayout" package="com.google.android.apps.magazines" content-desc="For You" checkable="false" checked="false" clickable="true" enabled="true" focusable="true" focused="false" scrollable="false" long-clickable="false" password="false" selected="false" bounds="[278,311][494,437]">
                        <node index="0" text="For You" resource-id="" class="android.widget.TextView" package="com.google.android.apps.magazines" content-desc="" checkable="false" checked="false" clickable="false" enabled="true" focusable="false" focused="false" scrollable="false" long-clickable="false" password="false" selected="false" bounds="[320,351][452,397]"/>
                      </node>
                      <node index="2" text="" resource-id="" class="android.widget.LinearLayout" package="com.google.android.apps.magazines" content-desc="Popular" checkable="false" checked="false" clickable="true" enabled="true" focusable="true" focused="false" scrollable="false" long-clickable="false" password="false" selected="false" bounds="[494,311][713,437]">
                        <node index="0" text="Popular" resource-id="" class="android.widget.TextView" package="com.google.android.apps.magazines" content-desc="" checkable="false" checked="false" clickable="false" enabled="true" focusable="false" focused="false" scrollable="false" long-clickable="false" password="false" selected="false" bounds="[536,351][671,397]"/>
                      </node>
                      <node index="3" text="" resource-id="" class="android.widget.LinearLayout" package="com.google.android.apps.magazines" content-desc="U.S." checkable="false" checked="false" clickable="true" enabled="true" focusable="true" focused="false" scrollable="false" long-clickable="false" password="false" selected="false" bounds="[713,311][866,437]">
                        <node index="0" text="U.S." resource-id="" class="android.widget.TextView" package="com.google.android.apps.magazines" content-desc="" checkable="false" checked="false" clickable="false" enabled="true" focusable="false" focused="false" scrollable="false" long-clickable="false" password="false" selected="false" bounds="[755,351][824,397]"/>
                      </node>
                      <node index="4" text="" resource-id="" class="android.widget.LinearLayout" package="com.google.android.apps.magazines" content-desc="World" checkable="false" checked="false" clickable="true" enabled="true" focusable="true" focused="false" scrollable="false" long-clickable="false" password="false" selected="false" bounds="[866,311][1056,437]">
                        <node index="0" text="World" resource-id="" class="android.widget.TextView" package="com.google.android.apps.magazines" content-desc="" checkable="false" checked="false" clickable="false" enabled="true" focusable="false" focused="false" scrollable="false" long-clickable="false" password="false" selected="false" bounds="[908,351][1014,397]"/>
                      </node>
                      <node index="5" text="" resource-id="" class="android.widget.LinearLayout" package="com.google.android.apps.magazines" content-desc="Politics" checkable="false" checked="false" clickable="true" enabled="true" focusable="true" focused="false" scrollable="false" long-clickable="false" password="false" selected="false" bounds="[1056,311][1080,437]"/>
                    </node>
                  </node>
                </node>
              </node>
              <node index="1" text="" resource-id="com.google.android.apps.magazines:id/section_pager" class="androidx.viewpager.widget.ViewPager" package="com.google.android.apps.magazines" content-desc="" checkable="false" checked="false" clickable="false" enabled="true" focusable="true" focused="false" scrollable="true" long-clickable="false" password="false" selected="false" bounds="[0,437][1080,1794]">
                <node index="0" text="" resource-id="com.google.android.apps.magazines:id/swipe_refresh_layout" class="android.view.ViewGroup" package="com.google.android.apps.magazines" content-desc="" checkable="false" checked="false" clickable="false" enabled="true" focusable="false" focused="false" scrollable="false" long-clickable="false" password="false" selected="false" bounds="[0,437][1080,1794]">
                  <node index="0" text="" resource-id="com.google.android.apps.magazines:id/recycler_view" class="android.widget.ListView" package="com.google.android.apps.magazines" content-desc="" checkable="false" checked="false" clickable="false" enabled="true" focusable="true" focused="false" scrollable="true" long-clickable="false" password="false" selected="false" bounds="[0,437][1080,1794]">
                    <node index="0" text="" resource-id="com.google.android.apps.magazines:id/card" class="android.widget.FrameLayout" package="com.google.android.apps.magazines" content-desc="" checkable="false" checked="false" clickable="false" enabled="true" focusable="false" focused="false" scrollable="false" long-clickable="false" password="false" selected="false" bounds="[0,490][1080,1327]">
                      <node index="0" text="" resource-id="com.google.android.apps.magazines:id/card_content" class="android.widget.LinearLayout" package="com.google.android.apps.magazines" content-desc="" checkable="false" checked="false" clickable="true" enabled="true" focusable="true" focused="false" scrollable="false" long-clickable="false" password="false" selected="false" bounds="[0,490][1080,1327]">
                        <node index="0" text="" resource-id="com.google.android.apps.magazines:id/image_container" class="android.widget.FrameLayout" package="com.google.android.apps.magazines" content-desc="" checkable="false" checked="false" clickable="false" enabled="true" focusable="false" focused="false" scrollable="false" long-clickable="false" password="false" selected="false" bounds="[0,490][1080,1037]">
                          <node index="0" text="" resource-id="com.google.android.apps.magazines:id/image" class="android.widget.ImageView" package="com.google.android.apps.magazines" content-desc="" checkable="false" checked="false" clickable="false" enabled="true" focusable="false" focused="false" scrollable="false" long-clickable="false" password="false" selected="false" bounds="[53,490][1027,1037]"/>
                        </node>
                        <node index="1" text="" resource-id="" class="android.widget.LinearLayout" package="com.google.android.apps.magazines" content-desc="" checkable="false" checked="false" clickable="false" enabled="true" focusable="false" focused="false" scrollable="false" long-clickable="false" password="false" selected="false" bounds="[0,1045][1080,1200]">
                          <node index="0" text="Trump’s Tariffs Have Sown Uncertainty. That Might Be the Point." resource-id="com.google.android.apps.magazines:id/title" class="android.widget.TextView" package="com.google.android.apps.magazines" content-desc="" checkable="false" checked="false" clickable="false" enabled="true" focusable="false" focused="false" scrollable="false" long-clickable="false" password="false" selected="false" bounds="[53,1045][1027,1200]"/>
                        </node>
                        <node index="4" text="" resource-id="" class="android.widget.LinearLayout" package="com.google.android.apps.magazines" content-desc="" checkable="false" checked="false" clickable="false" enabled="true" focusable="false" focused="false" scrollable="false" long-clickable="false" password="false" selected="false" bounds="[53,1200][1080,1327]">
                          <node index="0" text="39 minutes ago" resource-id="" class="android.widget.TextView" package="com.google.android.apps.magazines" content-desc="39 minutes ago" checkable="false" checked="false" clickable="false" enabled="true" focusable="false" focused="false" scrollable="false" long-clickable="false" password="false" selected="false" bounds="[53,1216][987,1311]"/>
                          <node index="1" text="" resource-id="com.google.android.apps.magazines:id/more_button" class="android.widget.Button" package="com.google.android.apps.magazines" content-desc="More options" checkable="false" checked="false" clickable="true" enabled="true" focusable="true" focused="false" scrollable="false" long-clickable="false" password="false" selected="false" bounds="[987,1216][1080,1311]"/>
                        </node>
                      </node>
                    </node>
                    <node index="1" text="" resource-id="com.google.android.apps.magazines:id/card" class="android.widget.FrameLayout" package="com.google.android.apps.magazines" content-desc="" checkable="false" checked="false" clickable="false" enabled="true" focusable="false" focused="false" scrollable="false" long-clickable="false" password="false" selected="false" bounds="[0,1391][1080,1794]">
                      <node index="0" text="" resource-id="com.google.android.apps.magazines:id/card_content" class="android.widget.LinearLayout" package="com.google.android.apps.magazines" content-desc="" checkable="false" checked="false" clickable="true" enabled="true" focusable="true" focused="false" scrollable="false" long-clickable="false" password="false" selected="false" bounds="[0,1391][1080,1794]">
                        <node index="0" text="" resource-id="com.google.android.apps.magazines:id/image_container" class="android.widget.FrameLayout" package="com.google.android.apps.magazines" content-desc="" checkable="false" checked="false" clickable="false" enabled="true" focusable="false" focused="false" scrollable="false" long-clickable="false" password="false" selected="false" bounds="[0,1391][1080,1794]">
                          <node index="0" text="" resource-id="com.google.android.apps.magazines:id/image" class="android.widget.ImageView" package="com.google.android.apps.magazines" content-desc="" checkable="false" checked="false" clickable="false" enabled="true" focusable="false" focused="false" scrollable="false" long-clickable="false" password="false" selected="false" bounds="[53,1391][1027,1794]"/>
                        </node>
                      </node>
                    </node>
                  </node>
                </node>
              </node>
            </node>
          </node>
        </node>
      </node>
    </node>
    <node index="1" text="" resource-id="android:id/navigationBarBackground" class="android.view.View" package="com.google.android.apps.magazines" content-desc="" checkable="false" checked="false" clickable="false" enabled="true" focusable="false" focused="false" scrollable="false" long-clickable="false" password="false" selected="false" bounds="[0,0][0,0]"/>
  </node>
</hierarchy>
